MANIFEST.in
setup.py
lessrb/__init__.py
lessrb/__init__.pyc
lessrb/__init__.py~
lessrb.egg-info/PKG-INFO
lessrb.egg-info/SOURCES.txt
lessrb.egg-info/dependency_links.txt
lessrb.egg-info/entry_points.txt
lessrb.egg-info/not-zip-safe
lessrb.egg-info/top_level.txt
lessrb/rb/.gitignore
lessrb/rb/CHANGELOG
lessrb/rb/LICENSE
lessrb/rb/README.md
lessrb/rb/Rakefile
lessrb/rb/VERSION
lessrb/rb/less.gemspec
lessrb/rb/bin/lessc
lessrb/rb/lib/less.rb
lessrb/rb/lib/less/command.rb
lessrb/rb/lib/less/engine.rb
lessrb/rb/lib/less/ext.rb
lessrb/rb/lib/less/engine/nodes.rb
lessrb/rb/lib/less/engine/grammar/common.tt
lessrb/rb/lib/less/engine/grammar/entity.tt
lessrb/rb/lib/less/engine/grammar/less.tt
lessrb/rb/lib/less/engine/nodes/element.rb
lessrb/rb/lib/less/engine/nodes/entity.rb
lessrb/rb/lib/less/engine/nodes/function.rb
lessrb/rb/lib/less/engine/nodes/literal.rb
lessrb/rb/lib/less/engine/nodes/property.rb
lessrb/rb/lib/less/engine/nodes/ruleset.rb
lessrb/rb/lib/less/engine/nodes/selector.rb
lessrb/rb/spec/command_spec.rb
lessrb/rb/spec/engine_spec.rb
lessrb/rb/spec/spec.css
lessrb/rb/spec/spec_helper.rb
lessrb/rb/spec/css/accessors.css
lessrb/rb/spec/css/big.css
lessrb/rb/spec/css/colors.css
lessrb/rb/spec/css/comments.css
lessrb/rb/spec/css/css-3.css
lessrb/rb/spec/css/css.css
lessrb/rb/spec/css/dash-prefix.css
lessrb/rb/spec/css/functions.css
lessrb/rb/spec/css/import-with-extra-paths.css
lessrb/rb/spec/css/import-with-partial-in-extra-path.css
lessrb/rb/spec/css/import.css
lessrb/rb/spec/css/lazy-eval.css
lessrb/rb/spec/css/mixins-args.css
lessrb/rb/spec/css/mixins.css
lessrb/rb/spec/css/operations.css
lessrb/rb/spec/css/parens.css
lessrb/rb/spec/css/rulesets.css
lessrb/rb/spec/css/scope.css
lessrb/rb/spec/css/selectors.css
lessrb/rb/spec/css/strings.css
lessrb/rb/spec/css/variables.css
lessrb/rb/spec/css/whitespace.css
lessrb/rb/spec/less/accessors.less
lessrb/rb/spec/less/big.less
lessrb/rb/spec/less/colors.less
lessrb/rb/spec/less/comments.less
lessrb/rb/spec/less/css-3.less
lessrb/rb/spec/less/css.less
lessrb/rb/spec/less/dash-prefix.less
lessrb/rb/spec/less/functions.less
lessrb/rb/spec/less/hidden.less
