Metadata-Version: 1.0
Name: lessrb
Version: 0.0.5
Summary: Wrapper for ruby less so that it's in a virtualenv.
Home-page: UNKNOWN
Author: Michael Axiak
Author-email: mike@axiak.net
License: Apache 2
Platform: UNKNOWN
